{
    "quantities": [
        {
            "trigger_column": "Heating",
            "initial": null,
            "final": "ASHPHeating",
            "order": ["LinearQuantity", "PercentQuantity"],
            "quantity_factors": [
                {
                    "type": "LinearQuantity",
                    "coefficient": 10000,
                    "indicator_cols": [
                        "feature.homeowner.in_bracket.AllCustomers"
                    ],
                    "error_scale": 0,
                    "description": "MassSave ASHP rebate for all customers",
                    "source": "MassSave",
                    "units": "$",
                    "per": "rebate"
                },
                {
                    "type": "LinearQuantity",
                    "coefficient": 15000,
                    "indicator_cols": [
                        "feature.homeowner.in_bracket.IncomeEligible"
                    ],
                    "error_scale": 0,
                    "description": "MassSave ASHP rebate for income eligible customers",
                    "source": "MassSave",
                    "units": "$",
                    "per": "rebate"
                },
                {
                    "type": "PercentQuantity",
                    "error_scale": 0,
                    "description": "IRA 30% tax credit for ASHP, capped at $2000",
                    "source": "IRA",
                    "percent": 0.3,
                    "limit": 2000,
                    "limit_unit": "USD"
                }
            ]
        },
        {
            "trigger_column": "Heating",
            "initial": null,
            "final": "GSHPHeating",
            "order": ["LinearQuantity", "PercentQuantity"],
            "quantity_factors": [
                {
                    "type": "LinearQuantity",
                    "coefficient": 15000,
                    "indicator_cols": [
                        "feature.homeowner.in_bracket.AllCustomers"
                    ],
                    "error_scale": 0,
                    "description": "MassSave GSHP rebate for all customers",
                    "source": "MassSave",
                    "units": "$",
                    "per": "rebate"
                },
                {
                    "type": "LinearQuantity",
                    "coefficient": 25000,
                    "indicator_cols": [
                        "feature.homeowner.in_bracket.IncomeEligible"
                    ],
                    "error_scale": 0,
                    "description": "MassSave GSHP rebate for income eligible customers",
                    "source": "MassSave",
                    "units": "$",
                    "per": "rebate"
                },
                {
                    "type": "PercentQuantity",
                    "error_scale": 0,
                    "description": "IRA 30% tax credit for GSHP, capped at $2000",
                    "source": "IRA",
                    "percent": 0.3,
                    "limit": 2000,
                    "limit_unit": "USD"
                }
            ]
        },
        {
            "trigger_column": "DHW",
            "initial": "ElectricResistanceDHW",
            "final": "HPWH",
            "order": ["LinearQuantity"],
            "quantity_factors": [
                {
                    "type": "LinearQuantity",
                    "coefficient": 750,
                    "indicator_cols": [
                        "feature.homeowner.in_bracket.AllCustomers"
                    ],
                    "error_scale": 0,
                    "description": "MassSave HPWH rebate for all customers",
                    "source": "MassSave",
                    "units": "$",
                    "per": "rebate"
                },
                {
                    "type": "LinearQuantity",
                    "coefficient": 1200,
                    "indicator_cols": [
                        "feature.homeowner.in_bracket.IncomeEligible"
                    ],
                    "error_scale": 0,
                    "description": "MassSave HPWH rebate for income eligible customers",
                    "source": "MassSave",
                    "units": "$",
                    "per": "rebate"
                }
            ]
        },
        {
            "trigger_column": "Thermostat",
            "initial": null,
            "final": "Controls",
            "order": ["LinearQuantity"],
            "quantity_factors": [
                {
                    "type": "LinearQuantity",
                    "coefficient": 100,
                    "indicator_cols": [
                        "feature.homeowner.in_bracket.AllCustomers"
                    ],
                    "error_scale": 0,
                    "description": "MassSave smart thermostat rebate for all customers",
                    "source": "MassSave",
                    "units": "$",
                    "per": "rebate"
                },
                {
                    "type": "LinearQuantity",
                    "coefficient": 200,
                    "indicator_cols": [
                        "feature.homeowner.in_bracket.IncomeEligible"
                    ],
                    "error_scale": 0,
                    "description": "MassSave smart thermostat rebate for income eligible customers",
                    "source": "MassSave",
                    "units": "$",
                    "per": "rebate"
                }
            ]
        },
        {
            "trigger_column": "Windows",
            "initial": null,
            "final": "DoublePaneLowE",
            "order": ["PercentQuantity"],
            "quantity_factors": [
                {
                    "type": "PercentQuantity",
                    "error_scale": 0,
                    "description": "IRA 30% tax credit for energy efficient windows, capped at $600",
                    "source": "IRA",
                    "percent": 0.3,
                    "limit": 600,
                    "limit_unit": "USD"
                }
            ]
        },
        {
            "trigger_column": "Windows",
            "initial": null,
            "final": "TriplePaneLowE",
            "order": ["PercentQuantity"],
            "quantity_factors": [
                {
                    "type": "PercentQuantity",
                    "error_scale": 0,
                    "description": "IRA 30% tax credit for energy efficient windows, capped at $600",
                    "source": "IRA",
                    "percent": 0.3,
                    "limit": 600,
                    "limit_unit": "USD"
                }
            ]
        }
    ],
    "output_key": "incentive",
    "raise_on_duplicate_trigger": false,
    "create_metadata": true,
    "metadata_aggregation": "bracket"
}
